fastauth/__init__.py
fastauth/_compat.py
fastauth/adapters/__init__.py
fastauth/adapters/base/__init__.py
fastauth/adapters/base/email_change.py
fastauth/adapters/base/email_verification.py
fastauth/adapters/base/oauth_accounts.py
fastauth/adapters/base/oauth_states.py
fastauth/adapters/base/password_reset.py
fastauth/adapters/base/refresh_tokens.py
fastauth/adapters/base/roles.py
fastauth/adapters/base/sessions.py
fastauth/adapters/base/token.py
fastauth/adapters/base/users.py
fastauth/adapters/sqlalchemy/__init__.py
fastauth/adapters/sqlalchemy/email_change.py
fastauth/adapters/sqlalchemy/email_verification.py
fastauth/adapters/sqlalchemy/models.py
fastauth/adapters/sqlalchemy/oauth_accounts.py
fastauth/adapters/sqlalchemy/oauth_states.py
fastauth/adapters/sqlalchemy/password_reset.py
fastauth/adapters/sqlalchemy/refresh_tokens.py
fastauth/adapters/sqlalchemy/roles.py
fastauth/adapters/sqlalchemy/sessions.py
fastauth/adapters/sqlalchemy/users.py
fastauth/api/__init__.py
fastauth/api/account.py
fastauth/api/adapter_factory.py
fastauth/api/auth.py
fastauth/api/dependencies.py
fastauth/api/oauth.py
fastauth/api/schemas.py
fastauth/api/sessions.py
fastauth/api/utils.py
fastauth/cli.py
fastauth/core/__init__.py
fastauth/core/account.py
fastauth/core/constants.py
fastauth/core/email_verification.py
fastauth/core/hashing.py
fastauth/core/oauth.py
fastauth/core/password_reset.py
fastauth/core/refresh_tokens.py
fastauth/core/roles.py
fastauth/core/sessions.py
fastauth/core/users.py
fastauth/email/__init__.py
fastauth/email/base.py
fastauth/email/console.py
fastauth/email/factory.py
fastauth/email/smtp.py
fastauth/email/utils.py
fastauth/providers/__init__.py
fastauth/providers/base.py
fastauth/providers/google.py
fastauth/security/__init__.py
fastauth/security/jwt.py
fastauth/security/limits.py
fastauth/security/oauth.py
fastauth/security/rate_limit.py
fastauth/security/tokens.py
fastauth/settings.py
sreekarnv_fastauth-0.2.6.dist-info/entry_points.txt
sreekarnv_fastauth-0.2.6.dist-info/LICENSE
sreekarnv_fastauth-0.2.6.dist-info/METADATA
sreekarnv_fastauth-0.2.6.dist-info/WHEEL
sreekarnv_fastauth-0.2.6.dist-info/RECORD
