Metadata-Version: 2.3
Name: sreekarnv-fastauth
Version: 0.2.6
Summary: Production-ready authentication for FastAPI applications
License: MIT
Keywords: fastapi,authentication,auth,jwt,oauth,rbac,session
Author: Sreekar Nutulapati
Author-email: sreekarnv1@gmail.com
Requires-Python: >=3.11
Classifier: Development Status :: 3 - Alpha
Classifier: Intended Audience :: Developers
Classifier: License :: OSI Approved :: MIT License
Classifier: Programming Language :: Python :: 3
Classifier: Programming Language :: Python :: 3.11
Classifier: Programming Language :: Python :: 3.12
Classifier: Programming Language :: Python :: 3.13
Classifier: Framework :: FastAPI
Classifier: Topic :: Software Development :: Libraries :: Python Modules
Classifier: Topic :: Internet :: WWW/HTTP
Classifier: Topic :: Security
Provides-Extra: all
Provides-Extra: cli
Provides-Extra: oauth
Requires-Dist: argon2-cffi (>=23.1.0)
Requires-Dist: email-validator (>=2.0.0)
Requires-Dist: httpx (>=0.27.0) ; extra == "all"
Requires-Dist: httpx (>=0.27.0) ; extra == "oauth"
Requires-Dist: itsdangerous (>=2.0.0)
Requires-Dist: pydantic-settings (>=2.0.0)
Requires-Dist: python-jose[cryptography] (>=3.3.0)
Requires-Dist: rich (>=13.0.0) ; extra == "all"
Requires-Dist: rich (>=13.0.0) ; extra == "cli"
Requires-Dist: sqlmodel (>=0.0.16)
Requires-Dist: typer (>=0.9.0) ; extra == "all"
Requires-Dist: typer (>=0.9.0) ; extra == "cli"
Project-URL: Bug Tracker, https://github.com/sreekarnv/fastauth/issues
Project-URL: Changelog, https://github.com/sreekarnv/fastauth/blob/main/CHANGELOG.md
Project-URL: Documentation, https://sreekarnv.github.io/fastauth/
Project-URL: Homepage, https://github.com/sreekarnv/fastauth
Project-URL: Repository, https://github.com/sreekarnv/fastauth
